{
  "questao_id": "2015_AR_D1_q055",
  "imagem": "q055.png",
  "ano": 2015,
  "aplicacao": "AR",
  "dia": "D1",
  "numero_azul": 55,
  "numero_amarela": null,
  "numero_rosa": null,
  "numero_branca": null,
  "numero_cinza": null,
  "disciplina": null,
  "conteudo": null,
  "gabarito": null,
  "tri_a": null,
  "tri_b": null,
  "tri_c": null,
  "fonte_classificacao": null,
  "texto_extraido": "QUESTÃO 55\t\nA hidroponia pode ser definida como uma técnica \nde produção de vegetais sem necessariamente a \npresença de solo. Uma das formas de implementação \né manter as plantas com suas raízes suspensas em \nmeio líquido, de onde retiram os nutrientes essenciais. \nSuponha que um produtor de rúcula hidropônica \nprecise ajustar a concentração do íon nitrato (NO3\n−) \npara 0,009 mol/L em um tanque de 5 000 litros e, para \ntanto, tem em mãos uma solução comercial nutritiva \nde nitrato de cálcio 90 g/L. As massas molares dos \nelementos N, O e Ca são iguais a 14 g/mol, 16 g/mol e \n40 g/mol, respectivamente.\nQual o valor mais próximo do volume da solução nutritiva, \nem litros, que o produtor deve adicionar ao tanque?\nA\t 26\nB\t 41\nC\t 45\nD\t 51\nE\t 82",
  "processado_em": "2026-05-08T14:00:47.363242",
  "_meta": {
    "pagina": 20,
    "coluna": "esquerda",
    "linha_x": 290.6
  }
}