{
  "questao_id": "2024_AR_D1_q023",
  "imagem": "q023.png",
  "ano": 2024,
  "aplicacao": "AR",
  "dia": "D1",
  "numero_azul": 23,
  "numero_amarela": null,
  "numero_rosa": null,
  "numero_branca": null,
  "numero_cinza": null,
  "disciplina": null,
  "conteudo": null,
  "gabarito": null,
  "tri_a": null,
  "tri_b": null,
  "tri_c": null,
  "fonte_classificacao": null,
  "texto_extraido": "QUESTÃO 23\t\nAs reações à sétima temporada foram o ápice do último \nestágio em Game of Thrones. De forma alguma, este que \nvos fala seria capaz de argumentar que a série é perfeita, \nmas os defeitos que existem aqui sempre existiram, de uma \nforma ou de outra, durante os sete anos em que ela esteve \nno ar. Os dois roteiristas foram brilhantes em traduzir os \npersonagens intrincados e conflituosos da obra de George \nR. R. Martin, mas nunca souberam exatamente como fazer \njus a eles (e especialmente a elas, as mulheres da trama).\nA verdade é que, com tudo isso e mais Ramin Djawadi \nevocando sentimentos e ambientes improváveis com sua \ntrilha sonora magistral, a série não conseguiria ser ruim nem \nse tentasse, mas continua sendo uma pena que, ao buscar \no seu final com tanta sede e tanta celeridade, Benioff e \nWeiss tenham tirado sua qualidade mais preciosa: o fôlego, \na paciência e o detalhismo que faziam suas palavras se \nlevantarem do papel e ganharem vida.\nDisponível em: https://observatoriodocinema.uol.com.br. \nAcesso em: 29 nov. 2017 (adaptado).\nAinda que faça uma avaliação positiva da série, nessa \nresenha, o autor aponta aspectos negativos da obra ao utilizar\nA\tmarcas de impessoalidade que disfarçam a opinião do \nespecialista.\nB\texpressões adversativas para fazer ressalvas às \nafirmações elogiosas.\nC\tinterlocução com o leitor para corroborar opiniões \ncontrárias à adaptação.\nD\teufemismos que minimizam as críticas feitas à \nconstrução das personagens.\nE\tantíteses que opõem a fragilidade do roteiro à beleza \nda trilha sonora da série.",
  "processado_em": "2026-05-08T14:06:09.998683",
  "_meta": {
    "pagina": 11,
    "coluna": "esquerda",
    "linha_x": 284.3
  }
}