{
  "questao_id": "2020_AR_D1_q014",
  "imagem": "q014.png",
  "ano": 2020,
  "aplicacao": "AR",
  "dia": "D1",
  "numero_azul": 14,
  "numero_amarela": null,
  "numero_rosa": null,
  "numero_branca": null,
  "numero_cinza": null,
  "disciplina": null,
  "conteudo": null,
  "gabarito": null,
  "tri_a": null,
  "tri_b": null,
  "tri_c": null,
  "fonte_classificacao": null,
  "texto_extraido": "A inter-relação entre tecnologia e sociedade tem \nestimulado a criação de aplicativos. Nesse texto, isso é \npercebido pelo desenvolvimento de aplicativos para\nA \t organização de eventos de competições esportivas.\nB \t agendamento de viagens para eventos de esporte \namador.\nC \t mapeamento dos interesses dos praticantes acerca \ndos esportes.\nD \t identificação da escassez de espaços para a vivência \ndos esportes.\nE \t formação de grupos em comunidades virtuais para a \nprática esportiva.\nQuestão 14          \nTEXTO I\nHIRST, D. Mother and Child. Bezerro dividido em duas partes: 1029 x \n1689 x 625mm, 1993 (detalhe). Vidro, aço pintado, silicone, acrílico, \nmonofilamento, aço inoxidável, bezerro e solução de formaldeído.\nTEXTO II\nO grupo Jovens Artistas Britânicos (YABs), que surgiu \nno final da década de 1980, possui obras diversificadas \nque incluem fotografias, instalações, pinturas e carcaças \ndesmembradas. O trabalho desses artistas chamou \na atenção no final do período da recessão, por utilizar \nmateriais incomuns, como esterco de elefantes, sangue \ne legumes, o que expressava os detritos da vida e uma \natmosfera de niilismo, temperada por um humor mordaz.\nDisponível em: http://damienhirst.com. Acesso em: 15 jul. 2015.\nFARTHING, S. Tudo sobre arte. Rio de Janeiro: Sextante, 2011 (adaptado).\nA provocação desse grupo gera um debate em torno da \nobra de arte pelo(a)\nA \t recusa a crenças, convicções, valores morais, \nestéticos e políticos na história moderna.\nB \t frutífero arsenal de materiais e formas que se \nrelacionam com os objetos construídos.\nC \t economia e problemas financeiros gerados pela \nrecessão que tiveram grande impacto no mercado.\nD \t influência desse grupo junto aos estilos pós-modernos \nque surgiram nos anos 1990.\nE \t interesse em produtos indesejáveis que revela uma \nconsciência sustentável no mercado.",
  "processado_em": "2026-05-11T23:27:59.365881",
  "_meta": {
    "pagina": 8,
    "coluna": "direita",
    "linha_x": 283.5
  }
}