{
  "questao_id": "2018_AR_D2_q094",
  "imagem": "q094.png",
  "ano": 2018,
  "aplicacao": "AR",
  "dia": "D2",
  "numero_azul": null,
  "numero_amarela": 94,
  "numero_rosa": null,
  "numero_branca": null,
  "numero_cinza": null,
  "disciplina": null,
  "conteudo": null,
  "gabarito": null,
  "tri_a": null,
  "tri_b": null,
  "tri_c": null,
  "fonte_classificacao": null,
  "texto_extraido": "QUESTÃO 94\n$\u0003LGHQWL¿FDomR\u0003GH\u0003ULVFRV\u0003GH\u0003SURGXWRV\u0003SHULJRVRV\u0003SDUD\u0003R\u0003\ntransporte rodoviário é obrigatória e realizada por meio da \nVLQDOL]DomR\u0003FRPSRVWD\u0003SRU\u0003XP\u0003SDLQHO\u0003GH\u0003VHJXUDQoD\u000f\u0003GH\u0003FRU\u0003\nalaranjada, e um rótulo de risco. As informações inseridas \nno painel de segurança e no rótulo de risco, conforme \nGHWHUPLQD\u0003 D\u0003 OHJLVODomR\u000f\u0003 SHUPLWHP\u0003 TXH\u0003 VH\u0003 LGHQWL¿TXH\u0003 R\u0003\nproduto transportado e os perigos a ele associados.\n$\u0003VLQDOL]DomR\u0003PRVWUDGD\u0003LGHQWL¿FD\u0003XPD\u0003VXEVWkQFLD\u0003TXH\u0003\nHVWi\u0003VHQGR\u0003WUDQVSRUWDGD\u0003HP\u0003XP\u0003FDPLQKmR\u0011\n2\nGÁS\nTÓXICO\n268\n1005\nOs três algarismos da parte superior do painel indicam \no “Número de risco”\u0011\u00032\u0003Q~PHUR\u0003\u0015\u0019\u001b\u0003LQGLFD\u0003WUDWDU\u0010VH\u0003GH\u0003XP\u0003\nJiV\u0003\u000b\u0015\f\u000f\u0003Wy[LFR\u0003\u000b\u0019\f\u0003H\u0003FRUURVLYR\u0003\u000b\u001b\f\u0011\u00032V\u0003TXDWUR\u0003GtJLWRV\u0003GD\u0003\nparte inferior correspondem ao “Número ONU”, que \nLGHQWL¿FD\u0003R\u0003SURGXWR\u0003WUDQVSRUWDGR\u0011\n%5$6,/\u0011\u0003Resolução n. 420\u000f\u0003GH\u0003\u0014\u0015\u0012\u0013\u0015\u0012\u0015\u0013\u0013\u0017\u000f\u0003GD\u0003$JrQFLD\u00031DFLRQDO\u0003GH\u00037UDQVSRUWHV\u00037HUUHVWUHV\u0003\n(ANTT)/Ministério dos Transportes (adaptado).\nABNT. NBR 7500\u001d\u0003LGHQWL¿FDomR\u0003SDUD\u0003R\u0003WUDQVSRUWH\u0003WHUUHVWUH\u000f\u0003PDQXVHLR\u000f\u0003PRYLPHQWDomR\u0003H\u0003\nDUPD]HQDPHQWR\u0003GH\u0003SURGXWRV\u0011\u00035LR\u0003GH\u0003-DQHLUR\u000f\u0003\u0015\u0013\u0013\u0017\u0003\u000bDGDSWDGR\f\u0011\n&RQVLGHUDQGR\u0003D\u0003LGHQWL¿FDomR\u0003DSUHVHQWDGD\u0003QR\u0003FDPLQKmR\u000f\u0003\no código 1005 corresponde à substância\nA eteno (C\u0015H\u0017).\nB nitrogênio (N\u0015).\nC amônia (NH3).\nD propano (C3H8).\nE dióxido de carbono (CO\u0015).",
  "processado_em": "2026-05-11T23:26:44.265640",
  "_meta": {
    "pagina": 2,
    "coluna": "direita",
    "linha_x": 314.1
  }
}