{
  "questao_id": "2016_AR_D1_q075",
  "imagem": "q075.png",
  "ano": 2016,
  "aplicacao": "AR",
  "dia": "D1",
  "numero_azul": 75,
  "numero_amarela": null,
  "numero_rosa": null,
  "numero_branca": null,
  "numero_cinza": null,
  "disciplina": null,
  "conteudo": null,
  "gabarito": null,
  "tri_a": null,
  "tri_b": null,
  "tri_c": null,
  "fonte_classificacao": null,
  "texto_extraido": "QUESTÃO 75\t\nA figura ilustra o movimento da seiva xilêmica em um\nCORRE\nMesmo que essa planta viesse a sofrer ação contínua\nseiva continuaria naturalmente seu percurso.\nO que garante o transporte dessa seiva é a\nA\t gutação.\nB\t gravidade.\nC\t respiração.\nD\t fotossíntese.\nE\t transpiração.",
  "processado_em": "2026-05-08T14:01:10.997843",
  "_meta": {
    "pagina": 26,
    "coluna": "esquerda",
    "linha_x": 314.1
  }
}