{
  "questao_id": "2017_2A_D1_q040",
  "imagem": "q040.png",
  "ano": 2017,
  "aplicacao": "2A",
  "dia": "D1",
  "numero_azul": 40,
  "numero_amarela": null,
  "numero_rosa": null,
  "numero_branca": null,
  "numero_cinza": null,
  "disciplina": null,
  "conteudo": null,
  "gabarito": null,
  "tri_a": null,
  "tri_b": null,
  "tri_c": null,
  "fonte_classificacao": null,
  "texto_extraido": "QUESTÃO 40\nAo longo dos anos 1980, um canal esportivo de \ntelevisão fracassou em implantar o basquete como esporte \nmundial, e uma empresa de materiais esportivos teve de \nlidar, fora do seu programa, com um esporte que lhe era \nestranho. Correndo atrás do prejuízo, ambas corrigiram \na rota e vieram a fazer da incorporação do futebol a seu \nprograma um objetivo estratégico alcançado com sucesso. \nO ajuste do interesse econômico à realidade cultural, no \nHQWDQWR\u000f\u0003QmR\u0003GHL[D\u0003GH\u0003GL]HU\u0003DOJR\u0003VREUH\u0003HOD\u001d\u0003p\u0003VLJQL¿FDWLYR\u0003\nque o mais mundial dos esportes não faça sentido para \nos Estados Unidos, e que os esportes que fazem mais \nsentido para os Estados Unidos estejam longe de fazer \nsentido para o mundo. O futebol ofereceu uma curiosa e \nnada desprezível contraparte simbólica à hegemonia do \nimaginário norte-americano.\n:,61,.\u000f\u0003-\u0011\u00030\u0011\u0003Veneno remédio: o futebol e o Brasil. \nSão Paulo: Cia. das Letras, 2008 (adaptado).\nDe acordo com o texto, em décadas passadas, a \nGL¿FXOGDGH\u0003 GDV\u0003 HPSUHVDV\u0003 QRUWH\u0010DPHULFDQDV\u0003 LQGLFD\u0003 D\u0003\nLQÀXrQFLD\u0003GH\u0003XP\u0003YLpV\u0003FXOWXUDO\u0003H\u0003HFRQ{PLFR\u0003QD\nA popularização do futebol no país frente à concorrência \ncom o basquete.\nB conquista da alta lucratividade por meio do futebol no \ncenário norte-americano.\nC implantação do basquete como esporte mundial \nfrente à força cultural do futebol.\nD LPSRUWkQFLD\u0003GDGD\u0003SRU\u0003HPSUHVDV\u0003HVSRUWLYDV\u0003DR\u0003IXWHERO\u000f\u0003\nsimilar àquela dada ao basquete.\nE tentativa de fazer com que o futebol transmitido pela \nTV seja consumido por sua população.",
  "processado_em": "2026-05-11T23:25:20.482468",
  "_meta": {
    "pagina": 17,
    "coluna": "esquerda",
    "linha_x": 314.1
  }
}