{
  "questao_id": "2017_2A_D1_q073",
  "imagem": "q073.png",
  "ano": 2017,
  "aplicacao": "2A",
  "dia": "D1",
  "numero_azul": 73,
  "numero_amarela": null,
  "numero_rosa": null,
  "numero_branca": null,
  "numero_cinza": null,
  "disciplina": null,
  "conteudo": null,
  "gabarito": null,
  "tri_a": null,
  "tri_b": null,
  "tri_c": null,
  "fonte_classificacao": null,
  "texto_extraido": "QUESTÃO 73\nAs rochas são desagregadas e decompostas e os \nmateriais resultantes de sua ação, tais como seixos, \ncascalhos, areias, siltes e argilas, são carregados e depois \nGHSRVLWDGRV\u0003H\u000f\u0003WDPEpP\u000f\u0003VXEVWkQFLDV\u0003GLVVROYLGDV\u0003QD\u0003iJXD\u0003\npodem precipitar. Em virtude de sua atuação, quaisquer \nrochas, independentemente de suas características, \nSRGHP\u0003¿FDU\u0003GHVWDFDGDV\u0003QR\u0003UHOHYR\u0011\nBELLOMO, H. R. et al. (Org.). 5LR\u0003*UDQGH\u0003GR\u00036XO\u001d\u0003DVSHFWRV\u0003GD\u0003JHRJUD¿D.\nPorto Alegre: Martins Livreiro, 1997 (adaptado).\nO texto refere-se à modelagem do relevo pelos processos \nnaturais de\nA magmatismo e fusão.\nB vulcanismo e erupção.\nC intemperismo e erosão.\nD tectonismo e subducção.\nE PHWDPRU¿VPR\u0003H\u0003UHFULVWDOL]DomR\u0011",
  "processado_em": "2026-05-11T23:25:22.929765",
  "_meta": {
    "pagina": 26,
    "coluna": "direita",
    "linha_x": 314.1
  }
}