{
  "questao_id": "2017_2A_D1_q089",
  "imagem": "q089.png",
  "ano": 2017,
  "aplicacao": "2A",
  "dia": "D1",
  "numero_azul": 89,
  "numero_amarela": null,
  "numero_rosa": null,
  "numero_branca": null,
  "numero_cinza": null,
  "disciplina": null,
  "conteudo": null,
  "gabarito": null,
  "tri_a": null,
  "tri_b": null,
  "tri_c": null,
  "fonte_classificacao": null,
  "texto_extraido": "QUESTÃO 89\nDisponível em: www1.folha.uol.com.br. Acesso em: 6 fev. 2014 (adaptado).\n2\u0003LPSDFWR\u0003DSUHVHQWDGR\u0003QHVVH\u0003DPELHQWH\u0003WHP\u0003VLGR\u0003LQWHQVL¿FDGR\u0003SHOD\nA intervenção direta do homem ao impermeabilizar o solo urbano.\nB irregularidade das chuvas decorrentes do fenômeno climático El Niño.\nC queima de combustíveis fósseis como o carvão, o petróleo e o gás natural.\nD vaporização crescente dos oceanos devido ao derretimento das geleiras.\nE extinção de organismos marinhos responsáveis pela produção de oxigênio.\nMoluscos\nPRINCIPAIS AFETADOS\n> Moluscos (mariscos, caramujos etc.)\n> Corais\n> Equinodermos (estrelas-do-mar)\n> Microrganismos com carapaça\nÍon carbonato\nH+\nCO2\nCO2\nCO2",
  "processado_em": "2026-05-11T23:25:24.013372",
  "_meta": {
    "pagina": 31,
    "coluna": "inteira",
    "linha_x": 314.1
  }
}