{
  "questao_id": "2025_AB_D1_q011",
  "imagem": "q011.png",
  "ano": 2025,
  "aplicacao": "AB",
  "dia": "D1",
  "numero_azul": 11,
  "numero_amarela": null,
  "numero_rosa": null,
  "numero_branca": null,
  "numero_cinza": null,
  "disciplina": null,
  "conteudo": null,
  "gabarito": null,
  "tri_a": null,
  "tri_b": null,
  "tri_c": null,
  "fonte_classificacao": null,
  "texto_extraido": "Questão 11\t\nTEXTO I\nDisponível em: https://jangada.online. Acesso em: 9 fev. 2024 (adaptado).\nTEXTO II\nÍndio eu não sou\nNão me chame de “índio” porque\nEsse nome nunca me pertenceu\nNem como apelido quero levar\nUm erro que Colombo cometeu.\nPor um erro de rota\nColombo em meu solo desembarcou\nE no desejo de às Índias chegar\nCom o nome de “índio” me apelidou.\n[...]\nChegou tarde, eu já estava aqui\nCaravela aportou bem ali\nEu vi “homem branco” subir\nNa minha Uka me escondi.\n[...]\n“Índio” eu não sou.\nSou Kambeba, sou Tembé\nSou Kokama, sou Sataré\nSou Guarani, sou Arawaté\nSou Tikuna, sou Suruí\nSou Tupinambá, sou Pataxó\nSou Terena, sou Tukano\nResisto com raça e fé.\nKAMBEBA, M. Ay Kakyri Tama: eu moro na cidade. \nSão Paulo: Pólen, 2018 (fragmento).\nEm relação aos povos originários, os textos I e II aproximam-se ao\nA\tenaltecer sua identidade.\nB\tdetalhar sua formação cultural.\nC\treconhecer o avanço de seus direitos.\nD\tdefender a demarcação de suas terras.\nE criticar o modo como são denominados",
  "processado_em": "2026-05-08T14:06:42.239004",
  "_meta": {
    "pagina": 8,
    "coluna": "esquerda",
    "linha_x": 287.0
  }
}