{
  "questao_id": "2023_AR_D1_q016",
  "imagem": "q016.png",
  "ano": 2023,
  "aplicacao": "AR",
  "dia": "D1",
  "numero_azul": 16,
  "numero_amarela": null,
  "numero_rosa": null,
  "numero_branca": null,
  "numero_cinza": null,
  "disciplina": null,
  "conteudo": null,
  "gabarito": null,
  "tri_a": null,
  "tri_b": null,
  "tri_c": null,
  "fonte_classificacao": null,
  "texto_extraido": "QUESTÃO 16\t\nMandioca, macaxeira, aipim e castelinha são nomes \ndiferentes da mesma planta. Semáforo, sinaleiro e farol \ntambém significam a mesma coisa. O que muda é só o \nhábito cultural de cada região. A mesma coisa acontece \ncom a Língua Brasileira de Sinais (Libras). Embora ela \nseja a comunicação oficial da comunidade surda no Brasil, \nexistem sinais que variam em relação à região, à idade e até \nao gênero de quem se comunica. A cor verde, por exemplo, \npossui sinais diferentes no Rio de Janeiro, Paraná e São \nPaulo. São os regionalismos na língua de sinais.\nEssas variações são um dos temas da disciplina \nLinguística na língua de sinais, oferecida pela Universidade \nEstadual Paulista (Unesp) ao longo do segundo semestre. \n“Muitas pessoas pensam que a língua de sinais é universal, \no que não é verdade”, explica a professora e chefe do \nDepartamento de Linguística, Literatura e Letras Clássicas \nda Unesp. “Mesmo dentro de um mesmo país, ela sofre \nvariação em relação à localização geográfica, à faixa etária \ne até ao gênero dos usuários”, completa a especialista.\nOs surdos podem criar sinais diferentes para identificar \nlugares, objetos e conceitos. Em São Paulo, o sinal de \n“cerveja” é feito com um giro do punho como uma meia-volta. \nEm Minas, a bebida é citada quando os dedos indicador e \nmédio batem no lado do rosto. Também ocorrem mudanças \nhistóricas. Um sinal pode sofrer alterações decorrentes dos \ncostumes da geração que o utiliza.\nDisponível em: www.educacao.sp.gov.br. Acesso em: 1 nov. 2021 (adaptado).\nNesse texto, a Língua Brasileira de Sinais (Libras)\nA\t\nA\t passa por fenômenos de variação linguística como \nqualquer outra língua.\nB\t\nB\t apresenta variações regionais, assumindo novo \nsentido para algumas palavras.\nC\t\nC\t sofre mudança estrutural motivada pelo uso de sinais \ndiferentes para algumas palavras.\nD\t\nD\t diferencia-se em todo o Brasil, desenvolvendo cada \nregião a sua própria língua de sinais.\nE\t\nE\t é ininteligível para parte dos usuários em razão das \nmudanças de sinais motivadas geograficamente.",
  "processado_em": "2026-05-08T14:05:34.913079",
  "_meta": {
    "pagina": 10,
    "coluna": "esquerda",
    "linha_x": 282.0
  }
}