{
  "questao_id": "2019_2A_D1_q039",
  "imagem": "q039.png",
  "ano": 2019,
  "aplicacao": "2A",
  "dia": "D1",
  "numero_azul": 39,
  "numero_amarela": null,
  "numero_rosa": null,
  "numero_branca": null,
  "numero_cinza": null,
  "disciplina": null,
  "conteudo": null,
  "gabarito": null,
  "tri_a": null,
  "tri_b": null,
  "tri_c": null,
  "fonte_classificacao": null,
  "texto_extraido": "Questão 39\t\nComo a percepção do tempo muda de acordo  \ncom a língua\nLínguas diferentes descrevem o tempo de maneiras \ndistintas — e as palavras usadas para falar sobre ele \nmoldam nossa percepção de sua passagem.\nO \nestudo \n“Distorção \ntemporal \nwhorfiana: \nrepresentando duração por meio da ampulheta da língua”, \npublicado no jornal da APA (Associação Americana de \nPsicologia), mostra que conceitos abstratos, como a \npercepção da duração do tempo, não são universais.\nOs autores não só verificaram uma mudança da \npercepção temporal conforme a língua falada como \nobservaram que a transição de uma língua para outra por \num mesmo indivíduo modificava sua estimativa de uma \nduração de tempo. Isso implica que visões diferentes de \ntempo convivem no cérebro de um indivíduo bilíngue.\n“O fato de que pessoas bilíngues transitam entre \nessas diferentes formas de estimar o tempo sem \nesforço e inconscientemente se encaixa nas evidências \ncrescentes que demonstram a facilidade com que a \nlinguagem se entremeia furtivamente em nossos sentidos \nmais básicos, incluindo nossas emoções, percepção \nvisual e, agora, ao que parece, nossa sensação de \ntempo”, disse o pesquisador ao site Quartz.\nLIMA, J. D. Disponível em: www.nexojornal.com.br. \n Acesso em: 24 ago. 2017.\nO texto relata experiências e resultados de um estudo \nque reconhece a importância\nA\t da compreensão do tempo pelo cérebro.\nB\t das pesquisas científicas sobre a cognição.\nC\t da teoria whorfiana para a área da linguagem.\nD\t das linguagens e seus usos na vida das pessoas.\nE\t do bilinguismo para o desenvolvimento intelectual.",
  "processado_em": "2026-05-11T23:26:57.993408",
  "_meta": {
    "pagina": 17,
    "coluna": "direita",
    "linha_x": 283.7
  }
}